MANIFEST.in
README.md
setup.cfg
setup.py
screeps/__init__.py
screeps/_version.py
screeps/screeps.py
screeps.egg-info/PKG-INFO
screeps.egg-info/SOURCES.txt
screeps.egg-info/dependency_links.txt
screeps.egg-info/requires.txt
screeps.egg-info/top_level.txt